LICENSE
MANIFEST.in
README.md
setup.py
./requirements.txt
upsonic/__init__.py
upsonic/remote/__init__.py
upsonic/remote/controller.py
upsonic/remote/helper.py
upsonic/remote/interface.py
upsonic/remote/ollama_langchain.py
upsonic/remote/on_prem.py
upsonic/remote/localimport/__init__.py
upsonic_legacy.egg-info/PKG-INFO
upsonic_legacy.egg-info/SOURCES.txt
upsonic_legacy.egg-info/dependency_links.txt
upsonic_legacy.egg-info/entry_points.txt
upsonic_legacy.egg-info/not-zip-safe
upsonic_legacy.egg-info/requires.txt
upsonic_legacy.egg-info/top_level.txt