Metadata-Version: 2.1
Name: upsonic-legacy
Version: 0.26.0
Summary: Magic Cloud Layer
Home-page: https://github.com/Upsonic/Upsonic
Author: Upsonic
Author-email: onur.atakan.ulusoy@upsonic.co
License: MIT
Platform: UNKNOWN
Requires-Python: >= 3
